{
  "Attacker": [
    {
      "component": 1,
      "features": [
        {
          "name": "Carries_Carries",
          "weight": 0.11305184682723293
        },
        {
          "name": "Att",
          "weight": 0.11240931545703226
        },
        {
          "name": "Total_Att",
          "weight": 0.11240931545703224
        },
        {
          "name": "Pass Types_Live",
          "weight": 0.11153870233639808
        }
      ]
    },
    {
      "component": 2,
      "features": [
        {
          "name": "Expected_xG",
          "weight": 0.1387285266392395
        },
        {
          "name": "Standard_Gls",
          "weight": 0.13759631689319496
        },
        {
          "name": "Performance_Gls",
          "weight": 0.13759631689319493
        },
        {
          "name": "Expected_npxG",
          "weight": 0.13366546133815274
        }
      ]
    }
  ],
  "Defender": [
    {
      "component": 1,
      "features": [
        {
          "name": "SCA_SCA",
          "weight": 0.11936571521211942
        },
        {
          "name": "SCA Types_PassLive",
          "weight": 0.11618660339471362
        },
        {
          "name": "Touches_Att 3rd",
          "weight": 0.11505774283770814
        },
        {
          "name": "KP",
          "weight": 0.10865561109427788
        }
      ]
    },
    {
      "component": 2,
      "features": [
        {
          "name": "Medium_Cmp",
          "weight": 0.13609640654686503
        },
        {
          "name": "Touches_Def 3rd",
          "weight": 0.13334293836824912
        },
        {
          "name": "Touches_Def Pen",
          "weight": 0.13211213576653189
        },
        {
          "name": "Total_PrgDist",
          "weight": 0.13000841238678773
        }
      ]
    }
  ],
  "Keeper": [
    {
      "component": 1,
      "features": [
        {
          "name": "Touches_Live",
          "weight": 0.14393066353913292
        },
        {
          "name": "Touches_Touches",
          "weight": 0.14393066353913292
        },
        {
          "name": "Touches_Def 3rd",
          "weight": 0.1437051958298318
        },
        {
          "name": "Att",
          "weight": 0.14351841211506855
        }
      ]
    },
    {
      "component": 2,
      "features": [
        {
          "name": "Total_Cmp%",
          "weight": 0.15757253321518697
        },
        {
          "name": "Total_Cmp_per90",
          "weight": 0.1505312491463282
        },
        {
          "name": "Outcomes_Cmp_per90",
          "weight": 0.15053124914632818
        },
        {
          "name": "Medium_Att_per90",
          "weight": 0.150424581736261
        }
      ]
    }
  ],
  "Midfielder": [
    {
      "component": 1,
      "features": [
        {
          "name": "Touches_Touches",
          "weight": 0.12918098839512582
        },
        {
          "name": "Touches_Live",
          "weight": 0.12916735240223895
        },
        {
          "name": "Total_Att",
          "weight": 0.12791234161540976
        },
        {
          "name": "Att",
          "weight": 0.12791234161540976
        }
      ]
    },
    {
      "component": 2,
      "features": [
        {
          "name": "Touches_Att Pen_per90",
          "weight": 0.1253315316145503
        },
        {
          "name": "Touches_Att Pen",
          "weight": 0.11939604400212032
        },
        {
          "name": "Per 90 Minutes_npxG+xAG",
          "weight": 0.1173021015122113
        },
        {
          "name": "Expected_npxG+xAG_per90",
          "weight": 0.11705454935213885
        }
      ]
    }
  ]
}